formic/LICENSE.txt
formic/VERSION.txt
formic/__init__.py
formic/command.py
formic/formic.py
formic_py3-0.1.0.dist-info/DESCRIPTION.rst
formic_py3-0.1.0.dist-info/METADATA
formic_py3-0.1.0.dist-info/RECORD
formic_py3-0.1.0.dist-info/WHEEL
formic_py3-0.1.0.dist-info/entry_points.txt
formic_py3-0.1.0.dist-info/metadata.json
formic_py3-0.1.0.dist-info/top_level.txt
formic_py3-0.1.0.dist-info/zip-safe
