Metadata-Version: 2.0
Name: formic-py3
Version: 0.1.0
Summary: An implementation of Apache Ant FileSet and Globs
Home-page: http://www.github.com/scottbelden/formic
Author: Scott Belden
Author-email: scott.a.belden@gmail.com
License: GPLv3+
Keywords: Apache Ant,glob,recurse,FileSet,file utilities,find
Platform: UNKNOWN
Classifier: License :: OSI Approved :: GNU General Public License v3 or later (GPLv3+)
Classifier: Programming Language :: Python
Classifier: Programming Language :: Python :: 2.7
Classifier: Programming Language :: Python :: 3
Classifier: Programming Language :: Python :: 3.5
Classifier: Development Status :: 4 - Beta
Classifier: Intended Audience :: Developers
Classifier: Topic :: Software Development :: Libraries
Requires-Dist: future
